Metadata-Version: 2.1
Name: odoo-addon-mgmtsystem
Version: 18.0.1.1.4
Requires-Python: >=3.10
Requires-Dist: odoo==18.0.*
Summary: Support for management systems, such as ISO compliance.
Home-page: https://github.com/OCA/management-system
License: AGPL-3
Author: Savoir-faire Linux,Odoo Community Association (OCA)
Author-email: support@odoo-community.org
Classifier: Programming Language :: Python
Classifier: Framework :: Odoo
Classifier: Framework :: Odoo :: 18.0
Classifier: License :: OSI Approved :: GNU Affero General Public License v3
